<?xml version="1.0" encoding="utf-8"?>
<result><name>Exhibit 30: Sustainability as a Function of Sustainability Planning and Specific Actions</name><data><row0 is_array="true"><item>Factors Predicting Sustainability</item><item>Type of Association</item></row0><row1 is_array="true"><item>Sustainability Plan Indicator</item><item>No Association</item></row1><row2 is_array="true"><item>Regular Attention to Sustainability Issues Indicator</item><item>Negative Association</item></row2><row3 is_array="true"><item>Reassessed Goals &amp;amp; Priorities</item><item>Positive Association</item></row3><row4 is_array="true"><item>Identified Effective Goals &amp;amp; Activities</item><item>No Association</item></row4><row5 is_array="true"><item>Developed Strategic Plan to Attain Resources</item><item>No Association</item></row5><row6 is_array="true"><item>Reduced Membership</item><item>Negative Association</item></row6><row7 is_array="true"><item>Reorganized Membership</item><item>No Association</item></row7><row8 is_array="true"><item>Restructured Coalition Operations</item><item>No Association</item></row8><row9 is_array="true"><item>Established Sustainability Committee</item><item>Negative Association</item></row9><row10 is_array="true"><item>Hired External Consultant for Sustainability</item><item>No Association</item></row10><row11 is_array="true"><item>Located Partners to Take Over Programs</item><item>No Association</item></row11><row12 is_array="true"><item>Developed Infrastructure in Community</item><item>Positive Association</item></row12><row13 is_array="true"><item>Ensured Mechanism for Policy Implementation &amp;amp; Enforcement</item><item>No Association</item></row13></data></result>
